greta/__init__.py
greta/checks.py
greta/conditionals.py
greta/errors.py
greta/query.py
greta/utils.py
greta-0.1.0.dist-info/LICENSE
greta-0.1.0.dist-info/METADATA
greta-0.1.0.dist-info/WHEEL
greta-0.1.0.dist-info/top_level.txt
greta-0.1.0.dist-info/RECORD
